enumify/__init__.py
enumify/_nbdev.py
enumify/enum.py
enumify/enumify.py
enumify/typing.py
enumify-0.0.1.dist-info/LICENSE
enumify-0.0.1.dist-info/METADATA
enumify-0.0.1.dist-info/WHEEL
enumify-0.0.1.dist-info/entry_points.txt
enumify-0.0.1.dist-info/top_level.txt
enumify-0.0.1.dist-info/RECORD
